vcfparser/__init__.py
vcfparser/meta_header_parser.py
vcfparser/metaviewer.py
vcfparser/record_parser.py
vcfparser/vcf_parser.py
vcfparser/vcf_writer.py
vcfparser-0.2.2.dist-info/LICENSE
vcfparser-0.2.2.dist-info/METADATA
vcfparser-0.2.2.dist-info/WHEEL
vcfparser-0.2.2.dist-info/top_level.txt
vcfparser-0.2.2.dist-info/RECORD
