Metadata-Version: 2.1
Name: vcfparser
Version: 0.2.2
Summary: Python (version <=3.12) package for parsing the genomics and transcriptomics VCF data.
Home-page: https://github.com/everestial/vcfparser
Author: Kiran Bishwa
Author-email: Kiran Bishwa <kirannbishwa01@gmail.com>
License: MIT License
Keywords: vcfparser
Classifier: Topic :: Scientific/Engineering :: Bio-Informatics
Classifier: License :: OSI Approved :: MIT License
Classifier: Natural Language :: English
Classifier: Programming Language :: Python :: 3
Classifier: Programming Language :: Python :: 3.8
Classifier: Programming Language :: Python :: 3.9
Classifier: Programming Language :: Python :: 3.10
Classifier: Programming Language :: Python :: 3.11
Classifier: Programming Language :: Python :: 3.12
License-File: LICENSE
